shlerp/__init__.py
shlerp/assets/rocket_shlerp.png
shlerp/bin/shlerp.py
shlerp/config/app_details.json
shlerp/config/rules.json
shlerp/config/settings.json
shlerp/docs/rulesystem.md
shlerp/docs/settings.md
shlerp/main.py
shlerp/tools/piputils.py
shlerp/tools/scan.py
shlerp/tools/state.py
shlerp/tools/utils.py
shlerp_cmd-1.5.post1.dist-info/LICENSE
shlerp_cmd-1.5.post1.dist-info/METADATA
shlerp_cmd-1.5.post1.dist-info/WHEEL
shlerp_cmd-1.5.post1.dist-info/entry_points.txt
shlerp_cmd-1.5.post1.dist-info/RECORD
